elkhound/__init__.py
elkhound/engine.py
elkhound/file.py
elkhound/logger.py
elkhound/runner.py
elkhound-0.0.4.dist-info/DESCRIPTION.rst
elkhound-0.0.4.dist-info/METADATA
elkhound-0.0.4.dist-info/RECORD
elkhound-0.0.4.dist-info/WHEEL
elkhound-0.0.4.dist-info/metadata.json
elkhound-0.0.4.dist-info/top_level.txt
