Metadata-Version: 2.0
Name: elkhound
Version: 0.0.4
Summary: Elkhound workflow engine
Home-page: https://github.com/elkhound/elkhound
Author: Lukasz Bolikowski
Author-email: lukasz@bolikowski.eu
License: UNKNOWN
Keywords: data,workflow,engine
Platform: UNKNOWN
Classifier: Programming Language :: Python
Classifier: Programming Language :: Python :: 3.5
Classifier: Programming Language :: Python :: 3.6
Classifier: Programming Language :: Python :: 3.7
Classifier: Development Status :: 3 - Alpha
Classifier: Environment :: Other Environment
Classifier: Intended Audience :: Developers
Classifier: License :: OSI Approved :: BSD License
Classifier: Operating System :: OS Independent
Classifier: Topic :: Software Development :: Libraries :: Python Modules
Classifier: Topic :: Scientific/Engineering :: Information Analysis
Requires-Dist: PyYAML
